README.md
setup.cfg
setup.py
cronjob/__init__.py
cronjob/types.py
cronjob.egg-info/PKG-INFO
cronjob.egg-info/SOURCES.txt
cronjob.egg-info/dependency_links.txt
cronjob.egg-info/entry_points.txt
cronjob.egg-info/not-zip-safe
cronjob.egg-info/requires.txt
cronjob.egg-info/top_level.txt
cronjob/apps/__init__.py
cronjob/apps/spider_app/__init__.py
cronjob/apps/spider_app/http.py
cronjob/apps/spider_app/proxy.py
cronjob/cli/__init__.py
cronjob/cli/cli.py
cronjob/core/__init__.py
cronjob/core/engine.py
cronjob/core/registry.py
cronjob/core/scheduler.py
cronjob/core/worker.py
cronjob/events/__init__.py
cronjob/events/actions.py
cronjob/events/event.py
cronjob/helpers/__init__.py
cronjob/helpers/user_agent.py
cronjob/queues/__init__.py
cronjob/queues/base.py
cronjob/queues/exceptions.py
cronjob/queues/local_queue.py
cronjob/queues/redis_queue.py
cronjob/settings/__init__.py
cronjob/settings/default_settings.py
cronjob/tasks/__init__.py
cronjob/tasks/tasks.py
cronjob/utils/__init__.py
cronjob/utils/cache.py
cronjob/utils/loaders.py
cronjob/utils/rule.py
cronjob/utils/tools.py
cronjob/utils/user_agents.py
cronjob/utils/utils.py