Metadata-Version: 1.2
Name: cronjob
Version: 0.0.20
Summary: A simple distributed `cron job` framework
Home-page: https://github.com/havefun-plus/cronjob
Author: fucangyu
Author-email: cangyufu@gmail.com
License: MIT
Platform: any
Requires-Python: >=3.6
